{
    "en": {
        "title": "Abdellah Edaoudi | Education",
        "description": "Explore the academic foundation of a Full Stack expert. Specialized Diploma in Digital Development, certified skills in React, Node.js, and modern web architecture.",
        "keywords": [
            "Digital Development Diploma",
            "Full Stack Certification",
            "Web Development Education",
            "Abdellah Edaoudi Degrees",
            "MERN Training"
        ]
    },
    "fr": {
        "title": "Abdellah Edaoudi | Éducation",
        "description": "Explorez la base académique d'un expert Full Stack. Diplôme de Technicien Spécialisé en Développement Digital, compétences certifiées en React, Node.js et architecture web moderne.",
        "keywords": [
            "Diplôme Développement Digital",
            "Certification Full Stack",
            "Formation Web Maroc",
            "Diplômes Abdellah Edaoudi",
            "Formation MERN"
        ]
    }
}